PyConsoleGraphics-0.1.dist-info/DESCRIPTION.rst
PyConsoleGraphics-0.1.dist-info/METADATA
PyConsoleGraphics-0.1.dist-info/RECORD
PyConsoleGraphics-0.1.dist-info/WHEEL
PyConsoleGraphics-0.1.dist-info/metadata.json
PyConsoleGraphics-0.1.dist-info/top_level.txt
pyconsolegraphics/__init__.py
pyconsolegraphics/ezmode.py
pyconsolegraphics/backends/__init__.py
pyconsolegraphics/backends/pygame.py
