Metadata-Version: 2.0
Name: PyConsoleGraphics
Version: 0.1
Summary: Portable, easy text-mode graphics
Home-page: UNKNOWN
Author: TOASTEngineer
Author-email: toastengineer@gmail.com
License: UNKNOWN
Platform: UNKNOWN
